docs/source/conf.py
src/auxetics-python/__init__.py
src/auxetics-python/example.py
auxetics_python-0.0.5.dist-info/METADATA
auxetics_python-0.0.5.dist-info/WHEEL
auxetics_python-0.0.5.dist-info/licenses/LICENSE
auxetics_python-0.0.5.dist-info/RECORD
